__init__.py
commands.py
main.py
cogo-0.0.1.dist-info/METADATA
cogo-0.0.1.dist-info/WHEEL
cogo-0.0.1.dist-info/entry_points.txt
cogo-0.0.1.dist-info/top_level.txt
cogo-0.0.1.dist-info/RECORD
