Metadata-Version: 2.1
Name: cogo
Version: 0.0.1
Requires-Dist: argparse
Requires-Dist: toml
